README.rst
qabal.py
setup.py
qabal.egg-info/PKG-INFO
qabal.egg-info/SOURCES.txt
qabal.egg-info/dependency_links.txt
qabal.egg-info/top_level.txt