Metadata-Version: 1.2
Name: qabal
Version: 0.0.4
Summary: A fast and simple message broker with content-based routing.
Home-page: https://www.phrostbyte.com/
Author: JJ Ben-Joseph
Author-email: opensource@phrostbyte.com
License: Apache
Keywords: broker routing content_based
Platform: UNKNOWN
Classifier: Topic :: Communications
Classifier: Development Status :: 2 - Pre-Alpha
Classifier: Intended Audience :: Developers
Classifier: License :: OSI Approved :: Apache Software License
Classifier: Programming Language :: Python :: 3 :: Only
Classifier: Programming Language :: Python :: 3.6
Classifier: Operating System :: OS Independent
Requires-Python: >=3.6
